terindo_single/__init__.py
terindo_single/detektor_single.py
terindo_single/download.py
terindo_single/emisi.py
terindo_single/klasifikasi.py
terindo_single/ocr.py
terindo_single/segmentasi.py
terindo_single/utils/__init__.py
terindo_single/utils/en_dict.txt
terindo_single/utils/geometry.py
terindo_single/utils/memory_cleanup.py
terindo_single/utils/object_classification.py
terindo_single/utils/object_detection.py
terindo_single/utils/object_detection_single.py
terindo_single/utils/object_segmentation.py
terindo_single/utils/ocr_process.py
terindo_single/utils/save.py
terindo_single/utils/sqldata.py
terindo_single-0.1.3.dist-info/License.txt
terindo_single-0.1.3.dist-info/METADATA
terindo_single-0.1.3.dist-info/WHEEL
terindo_single-0.1.3.dist-info/top_level.txt
terindo_single-0.1.3.dist-info/RECORD
